apiwatchdog/__init__.py
apiwatchdog/__main__.py
apiwatchdog/middleware_fastapi.py
apiwatchdog/middleware_flask.py
apiwatchdog/server.py
apiwatchdog/standalone_server.py
apiwatchdog/template_ui.py
apiwatchdog/watcher.py
live_api_monitor-0.1.0.dist-info/METADATA
live_api_monitor-0.1.0.dist-info/WHEEL
live_api_monitor-0.1.0.dist-info/top_level.txt
live_api_monitor-0.1.0.dist-info/RECORD
