Metadata-Version: 2.4
Name: live-api-monitor
Version: 0.1.0
Summary: Real-time API monitoring for Flask/FastAPI with async, zero-blocking logging
Home-page: https://github.com/mount-isaac/api-watch-dog
Author: Isaac Kyalo
Author-email: Isaac Kyalo <isadechair019@gmail.com>
License: MIT
Project-URL: Homepage, https://github.com/mount-isaac/api-watch-dog
Project-URL: Documentation, https://github.com/mount-isaac/api-watch-dog#readme
Project-URL: Repository, https://github.com/mount-isaac/api-watch-dog
Project-URL: Bug Tracker, https://github.com/mount-isaac/api-watch-dog/issues
Keywords: api,monitoring,flask,fastapi,logging,debugging,websocket,real-time
Classifier: Development Status :: 3 - Alpha
Classifier: Intended Audience :: Developers
Classifier: Topic :: Software Development :: Libraries :: Python Modules
Classifier: License :: OSI Approved :: MIT License
Classifier: Programming Language :: Python :: 3
Classifier: Programming Language :: Python :: 3.7
Classifier: Programming Language :: Python :: 3.8
Classifier: Programming Language :: Python :: 3.9
Classifier: Programming Language :: Python :: 3.11
Classifier: Programming Language :: Python :: 3.12
Classifier: Programming Language :: Python :: 3.13
Classifier: Framework :: Flask
Classifier: Framework :: FastAPI
Requires-Python: >=3.7
Requires-Dist: aiohttp>=3.8.0
Provides-Extra: dev
Requires-Dist: pytest>=7.0.0; extra == "dev"
Requires-Dist: pytest-asyncio>=0.20.0; extra == "dev"
Requires-Dist: black>=22.0.0; extra == "dev"
Requires-Dist: flake8>=5.0.0; extra == "dev"
Dynamic: author
Dynamic: home-page
Dynamic: requires-python
